yashiro/__init__.py
yashiro/main.py
yashiro/py.typed
yashiro-0.9.0.dist-info/entry_points.txt
yashiro-0.9.0.dist-info/LICENSE.txt
yashiro-0.9.0.dist-info/WHEEL
yashiro-0.9.0.dist-info/METADATA
yashiro-0.9.0.dist-info/RECORD
