Metadata-Version: 2.1
Name: yashiro
Version: 0.9.0
Summary: A cli template tool based on jinja
Home-page: https://github.com/spapanik/yashiro
License: LGPL-3.0+
Keywords: templates
Author: Stephanos Kuma
Author-email: stephanos@kuma.ai
Requires-Python: >=3.7.0,<4.0.0
Classifier: Development Status :: 3 - Alpha
Classifier: Intended Audience :: Developers
Classifier: License :: OSI Approved :: GNU Lesser General Public License v3 or later (LGPLv3+)
Classifier: Operating System :: OS Independent
Classifier: Programming Language :: Python :: 3
Classifier: Programming Language :: Python :: 3.10
Classifier: Programming Language :: Python :: 3.7
Classifier: Programming Language :: Python :: 3.8
Classifier: Programming Language :: Python :: 3.9
Requires-Dist: dj-settings (>=2.0.0,<3.0.0)
Requires-Dist: jinja2 (>=3.0.0,<4.0.0)
Project-URL: Repository, https://github.com/spapanik/yashiro
